subscriptable_path/__init__.py
subscriptable_path/_sp.py
subscriptable_path-0.1.0.dist-info/LICENSE
subscriptable_path-0.1.0.dist-info/METADATA
subscriptable_path-0.1.0.dist-info/WHEEL
subscriptable_path-0.1.0.dist-info/top_level.txt
subscriptable_path-0.1.0.dist-info/RECORD
