Metadata-Version: 2.1
Name: subscriptable-path
Version: 0.1.0
Summary: A subclass of Python's pathlib objects that allow subscripting/indexing.
Author: Douglas Thor
Author-email: Douglas Thor <doug.thor@gmail.com>
License: MIT License        
Project-URL: Source, https://github.com/dougthor42/subscriptable-path
Project-URL: Changelog, https://github.com/dougthor42/subscriptable-path/blob/master/CHANGELOG.md
Project-URL: Bug Tracker, https://github.com/dougtho42/subscriptable-path/issues
Keywords: path,pathlib
Classifier: Development Status :: 2 - Pre-Alpha
Classifier: Intended Audience :: Developers
Classifier: Intended Audience :: Information Technology
Classifier: Intended Audience :: System Administrators
Classifier: License :: OSI Approved :: MIT License
Classifier: Operating System :: Microsoft
Classifier: Operating System :: POSIX
Classifier: Programming Language :: Python :: 3 :: Only
Classifier: Topic :: System :: Operating System
Requires-Python: >=3.8
License-File: LICENSE
